Metadata-Version: 2.1
Name: WinWebV2
Version: 0.1.2
Summary: Create HTML User Interface using WinWebV2 in Python
Home-page: https://github.com/kxkx5150/WinWebV2
Author: Kunihiro Ando
Author-email: senna5150ando@gmail.com
License: MIT
Keywords: gui,html,javascript,electron
Platform: UNKNOWN
Classifier: Development Status :: 1 - Planning
Classifier: Operating System :: Microsoft :: Windows
Requires-Python: >=3.9
License-File: LICENSE
